hyperon_das_atomdb/__init__.py
hyperon_das_atomdb/adapters/__init__.py
hyperon_das_atomdb/adapters/redis_mongo_db.py
hyperon_das_atomdb/constants/__init__.py
hyperon_das_atomdb/constants/redis_mongo_db.py
hyperon_das_atomdb/exceptions.py
hyperon_das_atomdb/i_database.py
hyperon_das_atomdb/logger.py
hyperon_das_atomdb/utils/__init__.py
hyperon_das_atomdb/utils/expression_hasher.py
ca70c86b0bb3ef4272919ac95fe8809c1edb-0.1.0.dist-info/METADATA
ca70c86b0bb3ef4272919ac95fe8809c1edb-0.1.0.dist-info/WHEEL
ca70c86b0bb3ef4272919ac95fe8809c1edb-0.1.0.dist-info/RECORD
