Metadata-Version: 2.1
Name: ca70c86b0bb3ef4272919ac95fe8809c1edb
Version: 0.1.0
Summary: 
Author: marcocapozzoli
Author-email: marcocapozzoli90@gmail.com
Requires-Python: >=3.11,<4.0
Classifier: Programming Language :: Python :: 3
Classifier: Programming Language :: Python :: 3.11
Requires-Dist: pymongo (>=4.5.0,<5.0.0)
Requires-Dist: redis (>=5.0.0,<6.0.0)
